tunnelvision/__init__.py
tunnelvision/config.py
tunnelvision/definitions.py
tunnelvision/logger.py
tunnelvision/plot.py
tunnelvision/utils.py
tunnelvision/bin/tunnelvision-server
tunnelvision/bin/dist/index.html
tunnelvision/bin/dist/assets/bridge.78d53f15.js
tunnelvision/bin/dist/assets/index.58d42c0b.js
tunnelvision/bin/dist/assets/index.73b74798.css
tunnelvision/bin/dist/assets/tv.b4f81926.wasm
tunnelvision/server/__init__.py
tunnelvision/server/server.py
tunnelvision/server/state.py
tunnelvision-0.3.3.dist-info/LICENSE
tunnelvision-0.3.3.dist-info/METADATA
tunnelvision-0.3.3.dist-info/WHEEL
tunnelvision-0.3.3.dist-info/top_level.txt
tunnelvision-0.3.3.dist-info/RECORD
