Metadata-Version: 2.1
Name: tunnelvision
Version: 0.3.3
Summary: Experimental tensor viewer for IPython built on top of Voxel
Home-page: https://github.com/sluijs/tunnelvision
Author: Rogier van der Sluijs
License: GNU
Project-URL: Documentation, https://tunnelvision.readthedocs.io/
Classifier: Programming Language :: Python :: 3
Classifier: License :: OSI Approved :: GNU General Public License v3 (GPLv3)
Classifier: Operating System :: OS Independent
Requires-Python: >=3.6
License-File: LICENSE
Requires-Dist: dataclasses (>=0.6)
Requires-Dist: numpy
Requires-Dist: packaging
Requires-Dist: PyYAML (>=5.4.1)
Requires-Dist: tabulate
Requires-Dist: termcolor
Requires-Dist: websockets
Requires-Dist: shortuuid
Provides-Extra: dev
Requires-Dist: coverage ; extra == 'dev'
Requires-Dist: flake8 ; extra == 'dev'
Requires-Dist: flake8-bugbear ; extra == 'dev'
Requires-Dist: flake8-comprehensions ; extra == 'dev'
Requires-Dist: isort ; extra == 'dev'
Requires-Dist: black (==22.8.0) ; extra == 'dev'
Requires-Dist: click (==8.0.2) ; extra == 'dev'
Requires-Dist: pytest-cov (>=2.10.1) ; extra == 'dev'
Requires-Dist: pre-commit (>=2.9.3) ; extra == 'dev'
Requires-Dist: parameterized ; extra == 'dev'
Requires-Dist: twine ; extra == 'dev'
Provides-Extra: docs
Requires-Dist: mistune (<2.0.0,>=0.8.1) ; extra == 'docs'
Requires-Dist: sphinx ; extra == 'docs'
Requires-Dist: sphinxcontrib.bibtex ; extra == 'docs'
Requires-Dist: m2r2 ; extra == 'docs'
